MANIFEST.in
README.md
TODO.md
setup.cfg
setup.py
pain/__init__.py
pain/__init__.pyc
pain/files.py
pain/files.pyc
pain/scaffolds.py
pain/scaffolds.pyc
pain/templates.pyc
pain.egg-info/PKG-INFO
pain.egg-info/SOURCES.txt
pain.egg-info/dependency_links.txt
pain.egg-info/entry_points.txt
pain.egg-info/not-zip-safe
pain.egg-info/top_level.txt
pain/tests/__init__.py
pain/tests/__init__.pyc