Metadata-Version: 1.1
Name: pain
Version: 0.1
Summary: A scaffolding tool to mitigate the pain of setting up a new project.
Home-page: http://github.com/petermelias/pain
Author: Peter M. Elias
Author-email: petermelias@gmail.com
License: FreeBSD
Keywords: scaffolding scaffold python setup project new
Platform: any
Classifier: Development Status :: 3 - Alpha
Classifier: Environment :: Console
Classifier: Intended Audience :: Developers
Classifier: Programming Language :: Python
